zhmiscellanygsudo/__init__.py
zhmiscellanygsudo/_py_resources.py
zhmiscellanygsudo/_resource_files_lookup.py
zhmiscellanygsudo/_supportfuncs.py
zhmiscellanygsudo/admin_subprocess.py
zhmiscellanygsudo-0.6.1.dist-info/METADATA
zhmiscellanygsudo-0.6.1.dist-info/WHEEL
zhmiscellanygsudo-0.6.1.dist-info/top_level.txt
zhmiscellanygsudo-0.6.1.dist-info/RECORD
