Metadata-Version: 2.2
Name: zhmiscellanygsudo
Version: 0.6.1
Summary: A collection of python functions made by zh.
Home-page: https://discord.gg/ThBBAuueVJ
Author: zh
Author-email: imnotgivingmyemailjustaddmeondiscordmydiscordisz_h_@zh.com
Project-URL: Bug Tracker, https://github.com/zen-ham/zhmiscellanygsudo/issues
Classifier: Programming Language :: Python :: 3
Classifier: License :: OSI Approved :: MIT License
Classifier: Operating System :: Microsoft :: Windows
Requires-Python: >=3.6
Requires-Dist: zhmiscellany>=0
